chatbot/Dockerfile
chatbot/__about__.py
chatbot/__init__.py
chatbot/graph.py
chatbot/healthcheck.py
chatbot/utils/__init__.py
chatbot/utils/state.py
chatbot/utils/nodes/__init__.py
chatbot/utils/nodes/human_review.py
chatbot/utils/nodes/llm.py
chatbot/utils/tools/__init__.py
chatbot/utils/tools/multiply.py
chatbot/utils/tools/search.py
chatbot_nam685-0.0.9.dist-info/METADATA
chatbot_nam685-0.0.9.dist-info/WHEEL
chatbot_nam685-0.0.9.dist-info/licenses/LICENSE.txt
chatbot_nam685-0.0.9.dist-info/RECORD
