Metadata-Version: 2.4
Name: chatbot_nam685
Version: 0.0.9
Project-URL: Documentation, https://github.com/Nam Le/chatbot#readme
Project-URL: Issues, https://github.com/Nam Le/chatbot/issues
Project-URL: Source, https://github.com/Nam Le/chatbot
Author-email: Nam Le <lehainam2371999@gmail.com>
License-Expression: MIT
License-File: LICENSE.txt
Classifier: Development Status :: 4 - Beta
Classifier: Programming Language :: Python
Classifier: Programming Language :: Python :: 3.8
Classifier: Programming Language :: Python :: 3.9
Classifier: Programming Language :: Python :: 3.10
Classifier: Programming Language :: Python :: 3.11
Classifier: Programming Language :: Python :: 3.12
Classifier: Programming Language :: Python :: Implementation :: CPython
Classifier: Programming Language :: Python :: Implementation :: PyPy
Requires-Python: >=3.8
Requires-Dist: fastapi[standard]
Requires-Dist: grandalf
Requires-Dist: langchain-tavily
Requires-Dist: langchain[openai]
Requires-Dist: langgraph
Requires-Dist: pydantic
Requires-Dist: python-dotenv
Requires-Dist: uvicorn[standard]
